lukka_api/__init__.py
lukka_api/base_client.py
lukka_api/caching.py
lukka_api/decorators.py
lukka_api/distributed_lukka_api.py
lukka_api/file_utils.py
lukka_api/non_distributed_lukka_api.py
lukka_api/pagination.py
lukka_api/prices.py
lukka_api/sources.py
lukka_api/validators.py
lukka_api/write.py
lukka_api-0.1.7.dist-info/licenses/LICENSE
lukka_api-0.1.7.dist-info/METADATA
lukka_api-0.1.7.dist-info/WHEEL
lukka_api-0.1.7.dist-info/top_level.txt
lukka_api-0.1.7.dist-info/RECORD
