Metadata-Version: 2.4
Name: lukka-api
Version: 0.1.7
Summary: Python client for Lukka cryptocurrency data API
Home-page: https://github.com/KENOT-IO/lukka-api
Author: KENOT-IO
Author-email: KENOT-IO <du.tran@kenot.io>
Maintainer-email: KENOT-IO <vladimir.depoel@kenot.io>
License: MIT
Project-URL: Homepage, https://github.com/KENOT-IO/lukka-api
Project-URL: Documentation, https://github.com/KENOT-IO/lukka-api#readme
Project-URL: Repository, https://github.com/KENOT-IO/lukka-api
Project-URL: Bug Tracker, https://github.com/KENOT-IO/lukka-api/issues
Project-URL: Changelog, https://github.com/KENOT-IO/lukka-api/blob/main/CHANGELOG.md
Keywords: lukka,cryptocurrency,bitcoin,ethereum,crypto,api,data,finance
Classifier: Development Status :: 3 - Alpha
Classifier: Intended Audience :: Developers
Classifier: Intended Audience :: Financial and Insurance Industry
Classifier: Topic :: Office/Business :: Financial
Classifier: Topic :: Software Development :: Libraries :: Python Modules
Classifier: License :: OSI Approved :: MIT License
Classifier: Programming Language :: Python :: 3
Classifier: Programming Language :: Python :: 3.13
Classifier: Operating System :: OS Independent
Requires-Python: >=3.13
License-File: LICENSE
Requires-Dist: pandas>=2.3.0
Requires-Dist: numpy>=2.0.0
Requires-Dist: requests>=2.32.0
Requires-Dist: python-dotenv>=1.0.0
Requires-Dist: portalocker>=3.0.0
Requires-Dist: pyarrow>=22.0.0
Provides-Extra: dev
Requires-Dist: pytest>=7.0.0; extra == "dev"
Requires-Dist: pytest-cov>=4.0.0; extra == "dev"
Requires-Dist: black>=23.0.0; extra == "dev"
Requires-Dist: mypy>=1.0.0; extra == "dev"
Requires-Dist: bandit>=1.7.0; extra == "dev"
Requires-Dist: safety>=2.0.0; extra == "dev"
Provides-Extra: redis
Requires-Dist: redis>=5.0.0; extra == "redis"
Provides-Extra: all
Requires-Dist: redis>=5.0.0; extra == "all"
Dynamic: author
Dynamic: home-page
Dynamic: license-file
Dynamic: requires-python
